gargaml/__init__.py
gargaml-0.0.7.dist-info/LICENSE
gargaml-0.0.7.dist-info/METADATA
gargaml-0.0.7.dist-info/WHEEL
gargaml-0.0.7.dist-info/top_level.txt
gargaml-0.0.7.dist-info/RECORD
