Metadata-Version: 2.1
Name: gargaml
Version: 0.0.7
Summary: A personal ML lib
Home-page: https://github.com/AlexandreGazagnes/gargaml
Author: Alex Gazagnes
Author-email: <alex.gaz@email.com>
License: UNKNOWN
Keywords: python,machine learning
Platform: UNKNOWN
Classifier: Programming Language :: Python :: 3
Requires-Dist: pandas
Requires-Dist: numpy
Requires-Dist: Ipython
Requires-Dist: matplotlib
Requires-Dist: seaborn
Requires-Dist: plotly
Requires-Dist: missingno
Requires-Dist: scikit-learn
Requires-Dist: imbalanced-learn
Requires-Dist: category-encoders
Requires-Dist: requests
Requires-Dist: flask
Requires-Dist: flake8
Requires-Dist: pytest
Requires-Dist: pylint
Requires-Dist: black
Requires-Dist: scipy
Requires-Dist: statsmodels
Requires-Dist: lightgbm
Requires-Dist: xgboost
